setup.py
src/android/__init__.py
src/android/boot.py
src/android/command.py
src/android/exc.py
src/android/ota.py
src/android/tests/__init__.py
src/android/tests/mockzip.py
src/android/tests/test_ota.py
src/python_android.egg-info/PKG-INFO
src/python_android.egg-info/SOURCES.txt
src/python_android.egg-info/dependency_links.txt
src/python_android.egg-info/entry_points.txt
src/python_android.egg-info/requires.txt
src/python_android.egg-info/top_level.txt