Metadata-Version: 1.0
Name: python-android
Version: 1.1.0
Summary: A collection of Android tools written in Python.
Home-page: http://github.com/ctso/python-android
Author: Chris Soyars
Author-email: python@ctso.me
License: GNU GPL
Platform: UNKNOWN
Classifier: Development Status :: 2 - Pre-Alpha
Classifier: Intended Audience :: Developers
Classifier: License :: OSI Approved :: GNU General Public License (GPL)
Classifier: Topic :: Software Development :: Libraries
